MANIFEST.in
README.txt
bootstrap.py
buildout.cfg
setup.cfg
setup.py
collective/__init__.py
collective.hook.egg-info/PKG-INFO
collective.hook.egg-info/SOURCES.txt
collective.hook.egg-info/dependency_links.txt
collective.hook.egg-info/entry_points.txt
collective.hook.egg-info/namespace_packages.txt
collective.hook.egg-info/not-zip-safe
collective.hook.egg-info/paster_plugins.txt
collective.hook.egg-info/requires.txt
collective.hook.egg-info/top_level.txt
collective/hook/__init__.py
collective/hook/decorator.py
collective/hook/event.py
collective/hook/tests/__init__.py
collective/hook/tests/test_decorator.py
collective/hook/tests/test_event.py
collective/hook/tests/utils.py
docs/HISTORY.txt
docs/INSTALL.txt
docs/LICENSE.GPL
docs/LICENSE.txt