Metadata-Version: 1.0
Name: collective.hook
Version: 1.0b1
Summary: A very simple hook system for zope application by Makina-Corpus.
Home-page: http://svn.plone.org/svn/collective/collective.hook
Author: JeanMichel FRANCOIS aka toutpt
Author-email: toutpt@makina-corpus.org
License: GPL
Platform: UNKNOWN
Classifier: Framework :: Plone
Classifier: Programming Language :: Python
